pyriscope/__init__.py
pyriscope/__main__.py
pyriscope/processor.py
pyriscope/pyriscope.py
pyriscope-1.2.6.dist-info/DESCRIPTION.rst
pyriscope-1.2.6.dist-info/METADATA
pyriscope-1.2.6.dist-info/RECORD
pyriscope-1.2.6.dist-info/WHEEL
pyriscope-1.2.6.dist-info/entry_points.txt
pyriscope-1.2.6.dist-info/metadata.json
pyriscope-1.2.6.dist-info/top_level.txt
