Metadata-Version: 2.0
Name: pyriscope
Version: 1.2.6
Summary: A simple Periscope video downloader for Python.
Home-page: https://github.com/rharkanson/pyriscope
Author: Russell Harkanson
Author-email: rharkanson@gmail.com
License: MIT
Download-URL: https://github.com/rharkanson/pyriscope/tarball/1.2.6
Keywords: video,downloader,Periscope
Platform: UNKNOWN
Classifier: Programming Language :: Python
Classifier: Programming Language :: Python :: 3
Classifier: Programming Language :: Python :: 3 :: Only
Classifier: License :: OSI Approved :: MIT License
Classifier: Natural Language :: English
Classifier: Topic :: Multimedia :: Video
Classifier: Topic :: Multimedia :: Video :: Capture
Requires-Dist: python-dateutil
Requires-Dist: requests
Requires-Dist: six
Requires-Dist: wheel
